mobile_use_sdk/__init__.py
mobile_use_sdk/agent/__init__.py
mobile_use_sdk/agent/mobile_use_agent.py
mobile_use_sdk/agent/graph/__init__.py
mobile_use_sdk/agent/graph/builder.py
mobile_use_sdk/agent/graph/sse_output.py
mobile_use_sdk/agent/graph/state.py
mobile_use_sdk/agent/graph/nodes/__init__.py
mobile_use_sdk/agent/graph/nodes/compact.py
mobile_use_sdk/agent/graph/nodes/model.py
mobile_use_sdk/agent/graph/nodes/prepare.py
mobile_use_sdk/agent/graph/nodes/screenshot.py
mobile_use_sdk/agent/graph/nodes/should_react_continue.py
mobile_use_sdk/agent/graph/nodes/summary.py
mobile_use_sdk/agent/graph/nodes/tool.py
mobile_use_sdk/agent/history/__init__.py
mobile_use_sdk/agent/history/history.py
mobile_use_sdk/agent/infra/__init__.py
mobile_use_sdk/agent/infra/logger.py
mobile_use_sdk/agent/infra/message_web.py
mobile_use_sdk/agent/infra/model.py
mobile_use_sdk/agent/llm/__init__.py
mobile_use_sdk/agent/llm/ark_token.py
mobile_use_sdk/agent/llm/doubao.py
mobile_use_sdk/agent/llm/llm.py
mobile_use_sdk/agent/llm/stream_pipe.py
mobile_use_sdk/agent/mcp_hub/connection_pool_manager.py
mobile_use_sdk/agent/mcp_hub/global_connection_manager.py
mobile_use_sdk/agent/mcp_hub/mcp.py
mobile_use_sdk/agent/mcp_hub/mcp_connection_factory.py
mobile_use_sdk/agent/memory/__init__.py
mobile_use_sdk/agent/memory/messages.py
mobile_use_sdk/agent/memory/saver.py
mobile_use_sdk/agent/prompt/__init__.py
mobile_use_sdk/agent/prompt/doubao_tool_formatter.py
mobile_use_sdk/agent/prompt/doubao_vision_pro.py
mobile_use_sdk/agent/prompt/human_prompt.py
mobile_use_sdk/agent/prompt/summary.py
mobile_use_sdk/agent/tools/__init__.py
mobile_use_sdk/agent/tools/action_parser.py
mobile_use_sdk/agent/tools/model.py
mobile_use_sdk/agent/tools/tools.py
mobile_use_sdk/agent/tools/tool/__init__.py
mobile_use_sdk/agent/tools/tool/abc.py
mobile_use_sdk/agent/tools/tool/error.py
mobile_use_sdk/agent/tools/tool/finished.py
mobile_use_sdk/agent/tools/tool/mcp_tool.py
mobile_use_sdk/agent/tools/tool/request_user.py
ve_mobile_use-0.0.1.dist-info/licenses/LICENSE
ve_mobile_use-0.0.1.dist-info/METADATA
ve_mobile_use-0.0.1.dist-info/WHEEL
ve_mobile_use-0.0.1.dist-info/top_level.txt
ve_mobile_use-0.0.1.dist-info/RECORD
