Metadata-Version: 2.4
Name: ve-mobile-use
Version: 0.0.1
Summary: 云手机智能操作SDK，基于AI大模型实现云手机的自动化操作和智能交互
Author-email: Oanakiaja <oanakiaja@gmail.com>, sakia0z <sakia0z@163.com>
Maintainer-email: Oanakiaja <oanakiaja@gmail.com>, sakia0z <sakia0z@163.com>
License: Apache-2.0
Keywords: mobile,automation,ai,llm,cloud-phone,testing
Classifier: Development Status :: 4 - Beta
Classifier: Intended Audience :: Developers
Classifier: License :: OSI Approved :: Apache Software License
Classifier: Programming Language :: Python :: 3
Classifier: Programming Language :: Python :: 3.11
Classifier: Programming Language :: Python :: 3.12
Classifier: Topic :: Software Development :: Testing
Classifier: Topic :: Software Development :: Libraries :: Python Modules
Requires-Python: >=3.11
License-File: LICENSE
Requires-Dist: mcp>=1.9.4
Requires-Dist: tomli>=2.2.1
Requires-Dist: pydantic>=2.11.4
Requires-Dist: langgraph>=0.4.5
Requires-Dist: langchain-mcp-adapters>=0.1.0
Requires-Dist: httpx>=0.28.1
Requires-Dist: pillow>=11.2.1
Requires-Dist: openai>=1.90.0
Requires-Dist: langchain>=0.3.25
Requires-Dist: langchain-openai>=0.3.24
Requires-Dist: volcengine>=1.0.190
Requires-Dist: langchain-deepseek>=0.1.3
Requires-Dist: volcengine-python-sdk[ark]>=4.0.4
Requires-Dist: click>=8.1.0
Requires-Dist: psutil>=5.9.0
Requires-Dist: aiohttp>=3.8.0
Provides-Extra: dev
Requires-Dist: pytest>=8.4.1; extra == "dev"
Requires-Dist: pytest-asyncio>=0.24.0; extra == "dev"
Requires-Dist: python-dotenv>=1.0.0; extra == "dev"
Requires-Dist: ruff>=0.8.6; extra == "dev"
Requires-Dist: mypy>=1.8.0; extra == "dev"
Requires-Dist: pytest-cov>=4.1.0; extra == "dev"
Dynamic: license-file
